requests_cache/__init__.py
requests_cache/_utils.py
requests_cache/backends/__init__.py
requests_cache/backends/base.py
requests_cache/backends/dynamodb.py
requests_cache/backends/filesystem.py
requests_cache/backends/gridfs.py
requests_cache/backends/mongodb.py
requests_cache/backends/redis.py
requests_cache/backends/sqlite.py
requests_cache/cache_control.py
requests_cache/cache_keys.py
requests_cache/models/__init__.py
requests_cache/models/raw_response.py
requests_cache/models/request.py
requests_cache/models/response.py
requests_cache/patcher.py
requests_cache/py.typed
requests_cache/serializers/__init__.py
requests_cache/serializers/cattrs.py
requests_cache/serializers/pipeline.py
requests_cache/serializers/preconf.py
requests_cache/session.py
requests_cache-0.9.2.dist-info/LICENSE
requests_cache-0.9.2.dist-info/WHEEL
requests_cache-0.9.2.dist-info/METADATA
requests_cache-0.9.2.dist-info/RECORD
