Metadata-Version: 2.1
Name: requests-cache
Version: 0.9.2
Summary: A transparent persistent cache for the requests library
Home-page: https://github.com/reclosedev/requests-cache
License: BSD-2-Clause
Keywords: requests,cache,http,python-requests,web,performance,sqlite,redis,mongodb,gridfs,dynamodb
Author: Roman Haritonov
Maintainer: Jordan Cook
Requires-Python: >=3.7,<4.0
Classifier: Development Status :: 4 - Beta
Classifier: Intended Audience :: Developers
Classifier: License :: OSI Approved :: BSD License
Classifier: Programming Language :: Python :: 3
Classifier: Programming Language :: Python :: 3.7
Classifier: Programming Language :: Python :: 3.8
Classifier: Programming Language :: Python :: 3.9
Classifier: Programming Language :: Python :: 3.10
Classifier: Topic :: Software Development :: Libraries :: Python Modules
Classifier: Typing :: Typed
Provides-Extra: all
Provides-Extra: bson
Provides-Extra: docs
Provides-Extra: dynamodb
Provides-Extra: json
Provides-Extra: mongodb
Provides-Extra: redis
Provides-Extra: security
Provides-Extra: yaml
Requires-Dist: appdirs (>=1.4.4,<2.0.0)
Requires-Dist: attrs (>=21.2,<22.0)
Requires-Dist: boto3 (>=1.15,<2.0); extra == "dynamodb" or extra == "all"
Requires-Dist: botocore (>=1.18,<2.0); extra == "dynamodb" or extra == "all"
Requires-Dist: bson (>=0.5); extra == "bson"
Requires-Dist: cattrs (>=1.8,<2.0)
Requires-Dist: furo (>=2021.9.8); extra == "docs"
Requires-Dist: itsdangerous (>=2.0,<3.0); extra == "security" or extra == "all"
Requires-Dist: linkify-it-py (>=1.0.1,<2.0.0); extra == "docs"
Requires-Dist: myst-parser (>=0.15.1,<0.16.0); extra == "docs"
Requires-Dist: pymongo (>=3,<5); extra == "mongodb" or extra == "all"
Requires-Dist: pyyaml (>=5.4); extra == "yaml" or extra == "all"
Requires-Dist: redis (>=3,<5); extra == "redis" or extra == "all"
Requires-Dist: requests (>=2.22,<3.0)
Requires-Dist: sphinx (==4.3.0); extra == "docs"
Requires-Dist: sphinx-autodoc-typehints (>=1.11,<2.0); extra == "docs"
Requires-Dist: sphinx-automodapi (>=0.13,<0.15); extra == "docs"
Requires-Dist: sphinx-copybutton (>=0.3,<0.5); extra == "docs"
Requires-Dist: sphinx-inline-tabs (>=2022.1.2b11); (python_version >= "3.8") and (extra == "docs")
Requires-Dist: sphinx-notfound-page; extra == "docs"
Requires-Dist: sphinx-panels (>=0.6,<0.7); extra == "docs"
Requires-Dist: sphinxcontrib-apidoc (>=0.3,<0.4); extra == "docs"
Requires-Dist: ujson (>=4.0); extra == "json" or extra == "all"
Requires-Dist: url-normalize (>=1.4,<2.0)
Requires-Dist: urllib3 (>=1.25.5,<2.0.0)
Project-URL: Documentation, https://requests-cache.readthedocs.io
Project-URL: Repository, https://github.com/reclosedev/requests-cache
